{
  "context": {
    "date": "2026-05-06T19:37:02-06:00",
    "host_name": "node0.wolfiejk-304669.cs2640-pg0.utah.cloudlab.us",
    "executable": "bench",
    "num_cpus": 48,
    "mhz_per_cpu": 2795,
    "cpu_scaling_enabled": false,
    "caches": [
      {
        "type": "Data",
        "level": 1,
        "size": 32768,
        "num_sharing": 2
      },
      {
        "type": "Instruction",
        "level": 1,
        "size": 32768,
        "num_sharing": 2
      },
      {
        "type": "Unified",
        "level": 2,
        "size": 524288,
        "num_sharing": 2
      },
      {
        "type": "Unified",
        "level": 3,
        "size": 16777216,
        "num_sharing": 6
      }
    ],
    "load_avg": [
      0.00976562,
      3.09131,
      8.19873
    ],
    "library_version": "v1.9.1",
    "library_build_type": "release",
    "json_schema_version": 1
  },
  "benchmarks": [
    {
      "name": "hybrid_fill/iterations:1/real_time/threads:16",
      "family_index": 0,
      "per_family_instance_index": 0,
      "run_name": "hybrid_fill/iterations:1/real_time/threads:16",
      "run_type": "iteration",
      "repetitions": 1,
      "repetition_index": 0,
      "threads": 16,
      "iterations": 16,
      "real_time": 2557123604.6898775,
      "cpu_time": 2440728371.6875005,
      "time_unit": "ns",
      "items_per_second": 410060.7409344098,
      "peak_rss_mb": 2601.7265625,
      "wr_p50": 200.3761837021983,
      "wr_p99": 1142.5020617162843,
      "wr_p999": 4419.368294474733
    },
    {
      "name": "hybrid/real_time/threads:16",
      "family_index": 1,
      "per_family_instance_index": 0,
      "run_name": "hybrid/real_time/threads:16",
      "run_type": "iteration",
      "repetitions": 1,
      "repetition_index": 0,
      "threads": 16,
      "iterations": 23392368,
      "real_time": 621.0677478236753,
      "cpu_time": 621.0629035076739,
      "time_unit": "ns",
      "items_per_second": 1610130.3014110236,
      "peak_rss_mb": 2607.3515625,
      "rd_p50": 260.4890388128578,
      "rd_p99": 942.1258780140855,
      "rd_p999": 1172.558489271614,
      "wr_p50": 230.43261125752807,
      "wr_p99": 932.1070688289761,
      "wr_p999": 12961.11875400844
    }
  ]
}