{
  "context": {
    "date": "2026-05-03T18:43:39-06:00",
    "host_name": "node0.wolfiejk-303973.cs2640-pg0.utah.cloudlab.us",
    "executable": "bench",
    "num_cpus": 64,
    "mhz_per_cpu": 2346,
    "cpu_scaling_enabled": false,
    "caches": [
      {
        "type": "Data",
        "level": 1,
        "size": 32768,
        "num_sharing": 2
      },
      {
        "type": "Instruction",
        "level": 1,
        "size": 32768,
        "num_sharing": 2
      },
      {
        "type": "Unified",
        "level": 2,
        "size": 524288,
        "num_sharing": 2
      },
      {
        "type": "Unified",
        "level": 3,
        "size": 16777216,
        "num_sharing": 8
      }
    ],
    "load_avg": [
      3.88184,
      6.7998,
      5.38574
    ],
    "library_version": "v1.9.1",
    "library_build_type": "release",
    "json_schema_version": 1
  },
  "benchmarks": [
    {
      "name": "lockfree/real_time/threads:16",
      "family_index": 0,
      "per_family_instance_index": 0,
      "run_name": "lockfree/real_time/threads:16",
      "run_type": "iteration",
      "repetitions": 1,
      "repetition_index": 0,
      "threads": 16,
      "iterations": 14210848,
      "real_time": 506.47109862888504,
      "cpu_time": 506.4368853990978,
      "time_unit": "ns",
      "items_per_second": 1974446.3261718052,
      "rd_p50": 2080.6252032111156,
      "rd_p99": 16351.66758064605,
      "rd_p999": 20362.84010355797,
      "wr_p50": 1923.7255977230636,
      "wr_p99": 14114.14277194688,
      "wr_p999": 16992.909446553735
    },
    {
      "name": "lockfree_fill_presized/real_time/threads:16",
      "family_index": 1,
      "per_family_instance_index": 0,
      "run_name": "lockfree_fill_presized/real_time/threads:16",
      "run_type": "iteration",
      "repetitions": 1,
      "repetition_index": 0,
      "threads": 16,
      "iterations": 96,
      "real_time": 80313549.2498465,
      "cpu_time": 80306299.87500003,
      "time_unit": "ns",
      "items_per_second": 3264007.162533675,
      "wr_p50": 484.3422604196367,
      "wr_p99": 9782.349316081116,
      "wr_p999": 16187.94625318025
    },
    {
      "name": "lockfree_fill_resize/real_time/threads:16",
      "family_index": 2,
      "per_family_instance_index": 0,
      "run_name": "lockfree_fill_resize/real_time/threads:16",
      "run_type": "iteration",
      "repetitions": 1,
      "repetition_index": 0,
      "threads": 16,
      "iterations": 32,
      "real_time": 215792583.3739682,
      "cpu_time": 215773108.3125,
      "time_unit": "ns",
      "items_per_second": 1214796.152403926,
      "wr_p50": 3042.488002072648,
      "wr_p99": 30472.632074570676,
      "wr_p999": 67337.21764228496
    }
  ]
}