{
  "context": {
    "date": "2026-05-06T04:08:53-06:00",
    "host_name": "node0.wolfiejk-304669.cs2640-pg0.utah.cloudlab.us",
    "executable": "bench",
    "num_cpus": 48,
    "mhz_per_cpu": 2795,
    "cpu_scaling_enabled": false,
    "caches": [
      {
        "type": "Data",
        "level": 1,
        "size": 32768,
        "num_sharing": 2
      },
      {
        "type": "Instruction",
        "level": 1,
        "size": 32768,
        "num_sharing": 2
      },
      {
        "type": "Unified",
        "level": 2,
        "size": 524288,
        "num_sharing": 2
      },
      {
        "type": "Unified",
        "level": 3,
        "size": 16777216,
        "num_sharing": 6
      }
    ],
    "load_avg": [
      10.5742,
      13.7441,
      15.4375
    ],
    "library_version": "v1.9.1",
    "library_build_type": "release",
    "json_schema_version": 1
  },
  "benchmarks": [
    {
      "name": "ebr/real_time/threads:16",
      "family_index": 0,
      "per_family_instance_index": 0,
      "run_name": "ebr/real_time/threads:16",
      "run_type": "iteration",
      "repetitions": 1,
      "repetition_index": 0,
      "threads": 16,
      "iterations": 35611056,
      "real_time": 393.051656878103,
      "cpu_time": 393.0487608118111,
      "time_unit": "ns",
      "items_per_second": 2544194.8469132893,
      "peak_rss_mb": 436.4375,
      "rd_p50": 2885.415236287255,
      "rd_p99": 7694.440630099346,
      "rd_p999": 10419.555019926196,
      "wr_p50": 961.8050787624182,
      "wr_p99": 11541.66094514902,
      "wr_p999": 137578.20147464095
    },
    {
      "name": "ebr_fill_presized/real_time/threads:16",
      "family_index": 1,
      "per_family_instance_index": 0,
      "run_name": "ebr_fill_presized/real_time/threads:16",
      "run_type": "iteration",
      "repetitions": 1,
      "repetition_index": 0,
      "threads": 16,
      "iterations": 8048,
      "real_time": 1661356.8816677106,
      "cpu_time": 1661271.5116799255,
      "time_unit": "ns",
      "items_per_second": 2465454.6203753254,
      "peak_rss_mb": 399.75,
      "wr_p50": 641.2033858416124,
      "wr_p99": 7694.440630099346,
      "wr_p999": 82755.31198518307
    },
    {
      "name": "ebr_fill_resize/real_time/threads:16",
      "family_index": 2,
      "per_family_instance_index": 0,
      "run_name": "ebr_fill_resize/real_time/threads:16",
      "run_type": "iteration",
      "repetitions": 1,
      "repetition_index": 0,
      "threads": 16,
      "iterations": 3584,
      "real_time": 3939208.9949603,
      "cpu_time": 3938887.8443080327,
      "time_unit": "ns",
      "items_per_second": 1039802.6622198246,
      "peak_rss_mb": 17401.0,
      "wr_p50": 2885.415236287255,
      "wr_p99": 31436.140996931183,
      "wr_p999": 3804711.9655865133
    }
  ]
}