{
  "context": {
    "date": "2026-05-03T22:34:42-06:00",
    "host_name": "node0.wolfiejk-303973.cs2640-pg0.utah.cloudlab.us",
    "executable": "bench",
    "num_cpus": 64,
    "mhz_per_cpu": 2346,
    "cpu_scaling_enabled": false,
    "caches": [
      {
        "type": "Data",
        "level": 1,
        "size": 32768,
        "num_sharing": 2
      },
      {
        "type": "Instruction",
        "level": 1,
        "size": 32768,
        "num_sharing": 2
      },
      {
        "type": "Unified",
        "level": 2,
        "size": 524288,
        "num_sharing": 2
      },
      {
        "type": "Unified",
        "level": 3,
        "size": 16777216,
        "num_sharing": 8
      }
    ],
    "load_avg": [
      5.91602,
      5.22705,
      2.2417
    ],
    "library_version": "v1.9.1",
    "library_build_type": "release",
    "json_schema_version": 1
  },
  "benchmarks": [
    {
      "name": "lockfree/real_time/threads:8",
      "family_index": 0,
      "per_family_instance_index": 0,
      "run_name": "lockfree/real_time/threads:8",
      "run_type": "iteration",
      "repetitions": 1,
      "repetition_index": 0,
      "threads": 8,
      "iterations": 14817648,
      "real_time": 472.8643676117245,
      "cpu_time": 472.81575281043257,
      "time_unit": "ns",
      "items_per_second": 2114771.3139195847,
      "rd_p50": 1521.2440955033967,
      "rd_p99": 7773.352676350318,
      "rd_p999": 9540.178778302694,
      "wr_p50": 961.862858591834,
      "wr_p99": 6733.040010142838,
      "wr_p999": 71761.10880111204
    },
    {
      "name": "lockfree_fill_presized/real_time/threads:8",
      "family_index": 1,
      "per_family_instance_index": 0,
      "run_name": "lockfree_fill_presized/real_time/threads:8",
      "run_type": "iteration",
      "repetitions": 1,
      "repetition_index": 0,
      "threads": 8,
      "iterations": 56,
      "real_time": 149395118.73126322,
      "cpu_time": 149380053.98214284,
      "time_unit": "ns",
      "items_per_second": 3509405.156289653,
      "wr_p50": 242.17114524829864,
      "wr_p99": 4649.003816527197,
      "wr_p999": 16518.800794894512
    },
    {
      "name": "lockfree_fill_resize/real_time/threads:8",
      "family_index": 2,
      "per_family_instance_index": 0,
      "run_name": "lockfree_fill_resize/real_time/threads:8",
      "run_type": "iteration",
      "repetitions": 1,
      "repetition_index": 0,
      "threads": 8,
      "iterations": 24,
      "real_time": 290734550.0407246,
      "cpu_time": 290712022.2916665,
      "time_unit": "ns",
      "items_per_second": 1803321.9647494957,
      "wr_p50": 1360.9336190714246,
      "wr_p99": 13947.011449581592,
      "wr_p999": 32549.848438091747
    }
  ]
}